{
  "id": "bronze-butler",
  "name": "BRONZE BUTLER",
  "aliases": [
    "BRONZE BUTLER",
    "REDBALDKNIGHT",
    "Tick"
  ],
  "countryId": null,
  "orgId": null,
  "opTypes": [],
  "operationIds": [],
  "capabilityIds": [
    "cap-mimikatz",
    "cap-build-downer",
    "cap-cmd",
    "cap-abk",
    "cap-at",
    "cap-bbk",
    "cap-schtasks",
    "cap-down-new",
    "cap-daserf",
    "cap-net",
    "cap-shadowpad",
    "cap-windows-credential-editor",
    "cap-gsecdump",
    "cap-avenger"
  ],
  "description": "[BRONZE BUTLER](https://attack.mitre.org/groups/G0060) is a cyber espionage group with likely Chinese origins that has been active since at least 2008. The group primarily targets Japanese organizations, particularly those in government, biotechnology, electronics manufacturing, and industrial chemi",
  "confidence": "medium",
  "sources": [
    "https://attack.mitre.org/groups/G0060"
  ]
}
